Workbook

Sheet Cover Page
C3: Financial Modeling
C7: Get 10% OFF our course using coupon code EMAIL10
C9: Get our Complete Finance & Valuation Course
C11: Go to video file here
C13: Made by Career Principles Ltd.
C15: Note
C16: All content is copyright material of Career Principles Ltd.
C17: This Excel model may not be reproduced or distributed by any means, including printing, screencapturing, or any other method without the prior permission of the publisher.

Sheet START Cover
B2: =F6&" Financial Model" -> Nike Financial Model
B4: Scenario Analysis | E4: General Settings | H4: Table of Contents
B6: Live Scenario | C6: 1 | E6: Company Name | F6: Nike | H6: Cover Page
E7: Company Ticker | F7: ABC | H7: Income Statement
B8: Alerts | E8: Currency | F8: USD | H8: Balance Sheet
E9: Last Update | F9: 45870 | H9: Cash Flow Statement
B10: Balance Sheet Balances? | E10: Contact | F10: Johnson | H10: Assumptions & Drivers

Sheet START Forecast
B2: ="Income Statement of "&'START Cover'!F6 -> Income Statement of Nike
D3: 2023 | E3: =D3+1 -> 2024 | F3: =E3+1 -> 2025 | G3: =F3+1 -> 2026 | H3: =G3+1 -> 2027 | I3: =H3+1 -> 2028 | J3: =I3+1 -> 2029 | K3: =J3+1 -> 2030
B4: Revenue | D4: 5210 | E4: 5435 | F4: 5710 | G4: =F4*(1+G17) -> 6091.9538 | H4: =G4*(1+H17) -> 6499.4572 | I4: =H4*(1+I17) -> 6934.2194 | J4: =I4*(1+J17) -> 7398.0638 | K4: =J4*(1+K17) -> 7892.9356
B5: COGS | D5: 3345 | E5: 3350 | F5: 3551 | G5: =G18*G4 -> 3818.2362 | H5: =H18*H4 -> 4073.646 | I5: =I18*I4 -> 4346.1406 | J5: =J18*J4 -> 4636.863 | K5: =K18*K4 -> 4947.0324
B6: Gross Profit | D6: 1865 | E6: 2085 | F6: 2159 | G6: =G4-G5 -> 2273.7175 | H6: =H4-H5 -> 2425.8112 | I6: =I4-I5 -> 2588.0788 | J6: =J4-J5 -> 2761.2008 | K6: =K4-K5 -> 2945.9032
B7: SG&A | D7: 850 | E7: 870 | F7: 900 | G7: =G19*G4 -> 976.41754 | H7: =H19*H4 -> 1041.7321 | I7: =I19*I4 -> 1111.4158 | J7: =J19*J4 -> 1185.7607 | K7: =K19*K4 -> 1265.0787
B8: R&D | D8: 400 | E8: 420 | F8: 400 | G8: =G20*G4 -> 455.07886 | H8: =H20*H4 -> 485.52003 | I8: =I20*I4 -> 517.99747 | J8: =J20*J4 -> 552.6474 | K8: =K20*K4 -> 589.61513
B9: Operating Income | D9: 615 | E9: 795 | F9: 859 | G9: =G6-G7-G8 -> 842.22114 | H9: =H6-H7-H8 -> 898.55907 | I9: =I6-I7-I8 -> 958.66555 | J9: =J6-J7-J8 -> 1022.7927 | K9: =K6-K7-K8 -> 1091.2094
B10: Other income / (expense), net | D10: 50 | E10: 50 | F10: 50 | G10: =G21 -> 50 | H10: =H21 -> 50 | I10: =I21 -> 50 | J10: =J21 -> 50 | K10: =K21 -> 50
B11: Pre-tax income | D11: 565 | E11: 745 | F11: 809 | G11: =G9-G10 -> 792.22114 | H11: =H9-H10 -> 848.55907 | I11: =I9-I10 -> 908.66555 | J11: =J9-J10 -> 972.79268 | K11: =K9-K10 -> 1041.2094
B12: Taxes | D12: 227.5 | E12: 186.25 | F12: 147.25 | G12: =G11*G22 -> 198.05529 | H12: =H11*H22 -> 212.13977 | I12: =I11*I22 -> 227.16639 | J12: =J11*J22 -> 243.19817 | K12: =K11*K22 -> 260.30235
B13: Net Income | D13: 337.5 | E13: 558.75 | F13: 661.75 | G13: =G11-G12 -> 594.16586 | H13: =H11-H12 -> 636.4193 | I13: =I11-I12 -> 681.49916 | J13: =J11-J12 -> 729.59451 | K13: =K11-K12 -> 780.90706
B16: Income Statement Assumptions
B17: Revenue Growth Rate | E17: =E4/D4-1 -> 0.04318618 | F17: =F4/E4-1 -> 0.050597976 | G17: =CHOOSE('START Cover'!$C$6,'START Forecast'!G26,'START Forecast'!G27,'START Forecast'!G28) -> 0.066892078 | H17: =CHOOSE('START Cover'!$C$6,'START Forecast'!H26,'START Forecast'!H27,'START Forecast'!H28) -> 0.066892078 | I17: =CHOOSE('START Cover'!$C$6,'START Forecast'!I26,'START Forecast'!I27,'START Forecast'!I28) -> 0.066892078 | J17: =CHOOSE('START Cover'!$C$6,'START Forecast'!J26,'START Forecast'!J27,'START Forecast'!J28) -> 0.066892078 | K17: =CHOOSE('START Cover'!$C$6,'START Forecast'!K26,'START Forecast'!K27,'START Forecast'!K28) -> 0.066892078
B18: COGS as a % of Revenue | D18: =D5/D4 -> 0.64203455 | E18: =E5/E4 -> 0.61637534 | F18: =F5/F4 -> 0.62189142 | G18: =AVERAGE(D18:F18) -> 0.6267671 | H18: =G18 -> 0.6267671 | I18: =H18 -> 0.6267671 | J18: =I18 -> 0.6267671 | K18: =J18 -> 0.6267671
B19: SG&A as a % of Revenue | D19: =D7/D4 -> 0.16314779 | E19: =E7/E4 -> 0.1600736 | F19: =F7/F4 -> 0.15761821 | G19: =AVERAGE(D19:F19) -> 0.16027987 | H19: =G19 -> 0.16027987 | I19: =H19 -> 0.16027987 | J19: =I19 -> 0.16027987 | K19: =J19 -> 0.16027987
B20: R&D as a % of Revenue | D20: =D8/D4 -> 0.076775432 | E20: =E8/E4 -> 0.077276909 | F20: =F8/F4 -> 0.070052539 | G20: =AVERAGE(D20:F20) -> 0.074701627 | H20: =G20 -> 0.074701627 | I20: =H20 -> 0.074701627 | J20: =I20 -> 0.074701627 | K20: =J20 -> 0.074701627
B21: Other income / (expense), net | D21: =D10 -> 50 | E21: =E10 -> 50 | F21: =F10 -> 50 | G21: =F21 -> 50 | H21: =G21 -> 50 | I21: =H21 -> 50 | J21: =I21 -> 50 | K21: =J21 -> 50
B22: Tax Rate | D22: 0.25 | E22: =D22 -> 0.25 | F22: =E22 -> 0.25 | G22: =F22 -> 0.25 | H22: =G22 -> 0.25 | I22: =H22 -> 0.25 | J22: =I22 -> 0.25 | K22: =J22 -> 0.25
B25: Income Statement Assumptions
B26: Best Case | G26: =G27+2% -> 0.066892078 | H26: =H27+2% -> 0.066892078 | I26: =I27+2% -> 0.066892078 | J26: =J27+2% -> 0.066892078 | K26: =K27+2% -> 0.066892078
B27: Base Case | G27: =AVERAGE(E17:F17) -> 0.046892078 | H27: =G27 -> 0.046892078 | I27: =H27 -> 0.046892078 | J27: =I27 -> 0.046892078 | K27: =J27 -> 0.046892078
B28: Worst Case | G28: =G27-2% -> 0.026892078 | H28: =H27-2% -> 0.026892078 | I28: =I27-2% -> 0.026892078 | J28: =J27-2% -> 0.026892078 | K28: =K27-2% -> 0.026892078

Sheet END Cover
B2: =F6&" Financial Model" -> Nike Financial Model
B4: Scenario Analysis | E4: General Settings | H4: Table of Contents
B6: Live Scenario | C6: 3 | E6: Company Name | F6: Nike | H6: Cover Page
E7: Company Ticker | F7: ABC | H7: Income Statement
B8: Alerts | E8: Currency | F8: USD | H8: Balance Sheet
E9: Last Update | F9: 45870 | H9: Cash Flow Statement
B10: Balance Sheet Balances? | E10: Contact | F10: Johnson | H10: Assumptions & Drivers

Sheet END Forecast
B2: ="Income Statement of "&'END Cover'!F6 -> Income Statement of Nike
D3: 2023 | E3: =D3+1 -> 2024 | F3: =E3+1 -> 2025 | G3: =F3+1 -> 2026 | H3: =G3+1 -> 2027 | I3: =H3+1 -> 2028 | J3: =I3+1 -> 2029 | K3: =J3+1 -> 2030
B4: Revenue | D4: 5210 | E4: 5435 | F4: 5710 | G4: =F4*(1+G17) -> 5863.5538 | H4: =G4*(1+H17) -> 6021.2369 | I4: =H4*(1+I17) -> 6183.1605 | J4: =I4*(1+J17) -> 6349.4385 | K4: =J4*(1+K17) -> 6520.1881
B5: COGS | D5: 3345 | E5: 3350 | F5: 3551 | G5: =G18*G4 -> 3675.0826 | H5: =H18*H4 -> 3773.9132 | I5: =I18*I4 -> 3875.4016 | J5: =J18*J4 -> 3979.6192 | K5: =K18*K4 -> 4086.6394
B6: Gross Profit | D6: 1865 | E6: 2085 | F6: 2159 | G6: =G4-G5 -> 2188.4712 | H6: =H4-H5 -> 2247.3237 | I6: =I4-I5 -> 2307.7589 | J6: =J4-J5 -> 2369.8193 | K6: =K4-K5 -> 2433.5487
B7: Selling, general & administrative | D7: 850 | E7: 870 | F7: 900 | G7: =G19*G4 -> 939.80962 | H7: =H19*H4 -> 965.08306 | I7: =I19*I4 -> 991.03615 | J7: =J19*J4 -> 1017.6872 | K7: =K19*K4 -> 1045.0549
B8: Research & development | D8: 400 | E8: 420 | F8: 400 | G8: =G4*G20 -> 438.017 | H8: =H4*H20 -> 449.79619 | I8: =I4*I20 -> 461.89215 | J8: =J4*J20 -> 474.31339 | K8: =K4*K20 -> 487.06866
B9: Operating income | D9: 615 | E9: 795 | F9: 859 | G9: =G6-G7-G8 -> 810.64452 | H9: =H6-H7-H8 -> 832.44444 | I9: =I6-I7-I8 -> 854.8306 | J9: =J6-J7-J8 -> 877.81877 | K9: =K6-K7-K8 -> 901.42514
B10: Other income / (expense), net | D10: 50 | E10: 50 | F10: 50 | G10: =G21 -> 50 | H10: =H21 -> 50 | I10: =I21 -> 50 | J10: =J21 -> 50 | K10: =K21 -> 50
B11: Pre-tax income | D11: 565 | E11: 745 | F11: 809 | G11: =G9-G10 -> 760.64452 | H11: =H9-H10 -> 782.44444 | I11: =I9-I10 -> 804.8306 | J11: =J9-J10 -> 827.81877 | K11: =K9-K10 -> 851.42514
B12: Taxes | D12: 227.5 | E12: 186.25 | F12: 147.25 | G12: =G11*G22 -> 190.16113 | H12: =H11*H22 -> 195.61111 | I12: =I11*I22 -> 201.20765 | J12: =J11*J22 -> 206.95469 | K12: =K11*K22 -> 212.85629
B13: Net Income | D13: 337.5 | E13: 558.75 | F13: 661.75 | G13: =G11-G12 -> 570.48339 | H13: =H11-H12 -> 586.83333 | I13: =I11-I12 -> 603.62295 | J13: =J11-J12 -> 620.86408 | K13: =K11-K12 -> 638.56886
B16: Income Statement Assumptions
B17: Revenue Growth Rate | E17: =E4/D4-1 -> 0.04318618 | F17: =F4/E4-1 -> 0.050597976 | G17: =CHOOSE('END Cover'!$C$6,'END Forecast'!G26,'END Forecast'!G27,'END Forecast'!G28) -> 0.026892078 | H17: =CHOOSE('END Cover'!$C$6,'END Forecast'!H26,'END Forecast'!H27,'END Forecast'!H28) -> 0.026892078 | I17: =CHOOSE('END Cover'!$C$6,'END Forecast'!I26,'END Forecast'!I27,'END Forecast'!I28) -> 0.026892078 | J17: =CHOOSE('END Cover'!$C$6,'END Forecast'!J26,'END Forecast'!J27,'END Forecast'!J28) -> 0.026892078 | K17: =CHOOSE('END Cover'!$C$6,'END Forecast'!K26,'END Forecast'!K27,'END Forecast'!K28) -> 0.026892078
B18: COGS as a % of Revenue | D18: =D5/D4 -> 0.64203455 | E18: =E5/E4 -> 0.61637534 | F18: =F5/F4 -> 0.62189142 | G18: =AVERAGE(D18:F18) -> 0.6267671 | H18: =G18 -> 0.6267671 | I18: =H18 -> 0.6267671 | J18: =I18 -> 0.6267671 | K18: =J18 -> 0.6267671
B19: SG&A as % of Revenue | D19: =D7/D4 -> 0.16314779 | E19: =E7/E4 -> 0.1600736 | F19: =F7/F4 -> 0.15761821 | G19: =AVERAGE(D19:F19) -> 0.16027987 | H19: =G19 -> 0.16027987 | I19: =H19 -> 0.16027987 | J19: =I19 -> 0.16027987 | K19: =J19 -> 0.16027987
B20: R&D as % of Revenue | D20: =D8/D4 -> 0.076775432 | E20: =E8/E4 -> 0.077276909 | F20: =F8/F4 -> 0.070052539 | G20: =AVERAGE(D20:F20) -> 0.074701627 | H20: =G20 -> 0.074701627 | I20: =H20 -> 0.074701627 | J20: =I20 -> 0.074701627 | K20: =J20 -> 0.074701627
B21: Other income / (expense), net | D21: =D10 -> 50 | E21: =E10 -> 50 | F21: =F10 -> 50 | G21: =F21 -> 50 | H21: =G21 -> 50 | I21: =H21 -> 50 | J21: =I21 -> 50 | K21: =J21 -> 50
B22: Tax Rate | D22: 0.25 | E22: =D22 -> 0.25 | F22: =E22 -> 0.25 | G22: =F22 -> 0.25 | H22: =G22 -> 0.25 | I22: =H22 -> 0.25 | J22: =I22 -> 0.25 | K22: =J22 -> 0.25
B25: Revenue Scenarios
B26: Best Case | G26: =G27+2% -> 0.066892078 | H26: =H27+2% -> 0.066892078 | I26: =I27+2% -> 0.066892078 | J26: =J27+2% -> 0.066892078 | K26: =K27+2% -> 0.066892078
B27: Base Case Case | G27: =AVERAGE(E17:F17) -> 0.046892078 | H27: =G27 -> 0.046892078 | I27: =H27 -> 0.046892078 | J27: =I27 -> 0.046892078 | K27: =J27 -> 0.046892078
B28: Worst Case | G28: =G27-2% -> 0.026892078 | H28: =H27-2% -> 0.026892078 | I28: =I27-2% -> 0.026892078 | J28: =J27-2% -> 0.026892078 | K28: =K27-2% -> 0.026892078
